app_mqttc/__init__.py
app_mqttc/__main__.py
app_mqttc/main.py
app_mqttc/mqtt_task.py
app_mqttc-0.1.4.dist-info/entry_points.txt
app_mqttc-0.1.4.dist-info/WHEEL
app_mqttc-0.1.4.dist-info/METADATA
app_mqttc-0.1.4.dist-info/RECORD
