Metadata-Version: 2.1
Name: app-mqttc
Version: 0.1.4
Summary: 
Author: Ying Shaodong
Author-email: helloysd@foxmail.com
Requires-Python: >=3.6,<4.0
Classifier: Programming Language :: Python :: 3
Classifier: Programming Language :: Python :: 3.6
Classifier: Programming Language :: Python :: 3.7
Classifier: Programming Language :: Python :: 3.8
Classifier: Programming Language :: Python :: 3.9
Requires-Dist: importlib-metadata (>=1.0,<2.0); python_version < "3.8"
Requires-Dist: paho-mqtt (>=1.5.1,<2.0.0)
Requires-Dist: typer[all] (>=0.3.2,<0.4.0)
